fzh_xd_bigdata.py
fzh_bigdata3-1.0.dist-info/METADATA
fzh_bigdata3-1.0.dist-info/WHEEL
fzh_bigdata3-1.0.dist-info/top_level.txt
fzh_bigdata3-1.0.dist-info/RECORD
