Metadata-Version: 2.1
Name: fzh-bigdata3
Version: 1.0
Summary: 大数据1
Home-page: UNKNOWN
Author: 大数据1
Author-email: fzh@bigdata.com
License: UNKNOWN
Platform: UNKNOWN
